odoo8_addon_base_phone_popup-8.0.0.4.0.99.dev14-py2.7-nspkg.pth
odoo8_addon_base_phone_popup-8.0.0.4.0.99.dev14.dist-info/METADATA
odoo8_addon_base_phone_popup-8.0.0.4.0.99.dev14.dist-info/RECORD
odoo8_addon_base_phone_popup-8.0.0.4.0.99.dev14.dist-info/WHEEL
odoo8_addon_base_phone_popup-8.0.0.4.0.99.dev14.dist-info/namespace_packages.txt
odoo8_addon_base_phone_popup-8.0.0.4.0.99.dev14.dist-info/top_level.txt
odoo_addons/base_phone_popup/__init__.py
odoo_addons/base_phone_popup/__openerp__.py
odoo_addons/base_phone_popup/popup.py
odoo_addons/base_phone_popup/res_users_view.xml
odoo_addons/base_phone_popup/i18n/ar.po
odoo_addons/base_phone_popup/i18n/base_phone_popup.pot
odoo_addons/base_phone_popup/i18n/ca.po
odoo_addons/base_phone_popup/i18n/da.po
odoo_addons/base_phone_popup/i18n/de.po
odoo_addons/base_phone_popup/i18n/el_GR.po
odoo_addons/base_phone_popup/i18n/es.po
odoo_addons/base_phone_popup/i18n/es_ES.po
odoo_addons/base_phone_popup/i18n/fi.po
odoo_addons/base_phone_popup/i18n/fr.po
odoo_addons/base_phone_popup/i18n/fr_CH.po
odoo_addons/base_phone_popup/i18n/hr.po
odoo_addons/base_phone_popup/i18n/hr_HR.po
odoo_addons/base_phone_popup/i18n/it.po
odoo_addons/base_phone_popup/i18n/nl.po
odoo_addons/base_phone_popup/i18n/pt_BR.po
odoo_addons/base_phone_popup/i18n/sl.po
odoo_addons/base_phone_popup/i18n/tr.po
odoo_addons/base_phone_popup/i18n/tr_TR.po
odoo_addons/base_phone_popup/i18n/zh_CN.po
odoo_addons/base_phone_popup/static/description/icon.png
