Metadata-Version: 2.1
Name: odoo8-addon-base-phone-popup
Version: 8.0.0.4.0.99.dev14
Summary: Pop-up the related form view to the user on incoming calls
Home-page: http://www.akretion.com/
Author: Akretion,Odoo Community Association (OCA)
Author-email: support@odoo-community.org
License: AGPL-3
Platform: UNKNOWN
Classifier: Programming Language :: Python
Classifier: Framework :: Odoo
Classifier: License :: OSI Approved :: GNU Affero General Public License v3
Requires-Python: ~=2.7
Requires-Dist: odoo8-addon-base-phone
Requires-Dist: odoo8-addon-web-action-request
Requires-Dist: odoo (<9.0a,>=8.0a)
